[
  {
    "LiveFrom": "29/03/2019",
    "CaseTypeID": "DIVORCE_BulkAction",
    "ID": "CaseHistory",
    "Label": "History",
    "FieldType": "CaseHistoryViewer",
    "SecurityClassification": "Public"
  },
  {
    "LiveFrom": "01/01/2019",
    "CaseTypeID": "DIVORCE_BulkAction",
    "ID": "CaseTitle",
    "Label": "Case title",
    "FieldType": "Text",
    "SecurityClassification": "Public"
  },
  {
    "LiveFrom": "01/01/2019",
    "CaseTypeID": "DIVORCE_BulkAction",
    "ID": "CourtName",
    "Label": "Court name",
    "FieldType": "FixedList",
    "FieldTypeParameter": "DnCourtEnum",
    "SecurityClassification": "Public"
  },
  {
    "LiveFrom": "01/01/2019",
    "CaseTypeID": "DIVORCE_BulkAction",
    "ID": "hearingDate",
    "Label": "Hearing Date",
    "FieldType": "DateTime",
    "SecurityClassification": "Public"
  },
  {
    "LiveFrom": "01/01/2019",
    "CaseTypeID": "DIVORCE_BulkAction",
    "ID": "CaseList",
    "Label": "Case list",
    "FieldType": "Collection",
    "FieldTypeParameter": "DivorceCaseList",
    "SecurityClassification": "Public"
  },
  {
    "LiveFrom": "01/01/2019",
    "CaseTypeID": "DIVORCE_BulkAction",
    "ID": "CaseAcceptedList",
    "Label": "Cases accepted to list for hearing",
    "FieldType": "Collection",
    "FieldTypeParameter": "CaseLink",
    "SecurityClassification": "Public"
  },
  {
    "LiveFrom": "01/01/2019",
    "CaseTypeID": "DIVORCE_BulkAction",
    "ID": "DecreeNisiGrantedDate",
    "Label": "Decree Nisi Pronouncement Date",
    "FieldType": "Date",
    "SecurityClassification": "Public"
  },
  {
    "LiveFrom": "01/01/2019",
    "CaseTypeID": "DIVORCE_BulkAction",
    "ID": "DAEligibleFromDate",
    "Label": "Decree Absolute Eligible From Date",
    "FieldType": "Date",
    "SecurityClassification": "Public"
  },
  {
    "LiveFrom": "01/01/2019",
    "CaseTypeID": "DIVORCE_BulkAction",
    "ID": "PronouncementJudge",
    "Label": "Pronouncement Judge",
    "FieldType": "Text",
    "SecurityClassification": "Public"
  },
  {
    "LiveFrom": "01/01/2017",
    "CaseTypeID": "DIVORCE_BulkAction",
    "ID": "D8DocumentsGenerated",
    "Label": "Documents generated",
    "FieldType": "Collection",
    "FieldTypeParameter": "BulkListDocument",
    "SecurityClassification": "Public"
  }
]
